prisma_flow_diagram/__init__.py
prisma_flow_diagram/cli.py
prisma_flow_diagram/colrev.py
prisma_flow_diagram/loader.py
prisma_flow_diagram/prisma.py
prisma_flow_diagram/validation.py
prisma_flow_diagram-0.1.0.dist-info/METADATA
prisma_flow_diagram-0.1.0.dist-info/WHEEL
prisma_flow_diagram-0.1.0.dist-info/entry_points.txt
prisma_flow_diagram-0.1.0.dist-info/licenses/LICENSE
prisma_flow_diagram-0.1.0.dist-info/RECORD
