Metadata-Version: 2.4
Name: prisma-flow-diagram
Version: 0.1.0
Summary: A Python package to create PRISMA flow diagrams
Project-URL: repository, https://github.com/CoLRev-Environment/prisma-flow-diagram
Author-email: Gerit Wagner <gerit.wagner@uni-bamberg.de>
License: MIT
License-File: LICENSE
Requires-Python: <4,>=3.8
Requires-Dist: matplotlib>=3.5
